EXTENDER.v
module EXTENDER (   input Ki,Li, // Creacion del Bloque EXTENDER y sus entradas y salidas
				   input A,B,
				   output K_n,L_n );

 assign K_n = ((A & !B ) | (!B & Ki) | (Ki & (A)) ); //funcion logica para la salida final K de cada bloque EXTENDER

 assign L_n = ((!A & B ) | (Li & !A) | (B & (Li)) ); //funcion logica para la salida final L de cada bloque EXTENDER

endmodule

MUX4x1_Case.v
module MUX4x1_Case ( input [3:0] I,
					 input [1:0] S,
					 output reg T);

always @ (*) //Escoge que valor mostrar en la entrada dependiendo de 2 bits de el vector S
	case (S)
		2'd0 : T = I[0];
		2'd1 : T = I[1];
		2'd2 : T = I[2];
		2'd3 : T = I[3];
	endcase
endmodule

COMPARATOR.v
`include "MUX4x1_Case.v"

module COMPARATOR( input [1:0] s, // Creacion del Bloque COMPARATOR y sus salidas
				   output  K,L);

 parameter a = 1'b1;
 parameter b = 1'b0; // Posiciones de seleccion del primer MUX 4x1
 parameter c = 1'b1;
 parameter d = 1'b1;

 parameter e = 1'b1;
 parameter f = 1'b1;
 parameter g = 1'b0;// Posiciones de seleccion del segundo MUX 4x1
 parameter h = 1'b1;

 MUX4x1_Case MUX4x1_K (.I({a, b, c, d}), .S({s[0], s[1]}), .T(K));  //Instanciacion de los dos MUX4x1 para K y L
 MUX4x1_Case MUX4x1_L (.I({e, f, g, h}), .S({s[0], s[1]}), .T(L));
endmodule

COMP_4.v
`include "COMPARATOR.v"
`include "EXTENDER.v"
module COMP_4(input [3:0] X, //Creacion del bloque COMP_4
			  input [3:0] Y,
			  output K_o, L_o
			  );
	wire wk0, wk1, wk2;  //conexiones internas del sistema a simular
	wire wl0, wl1, wl2;

	COMPARATOR Comp_1 (.s({X[0],Y[0]}), .K(wk0), .L(wl0));  // instanciacion de todos los bloques 
	EXTENDER Ext_1 (.Ki(wk0),.Li(wl0),.A(X[1]),.B(Y[1]),.K_n(wk1),.L_n(wl1)); // necesarios para la estructura
	EXTENDER Ext_2 (.Ki(wk1),.Li(wl1),.A(X[2]),.B(Y[2]),.K_n(wk2),.L_n(wl2));
	EXTENDER Ext_3 (.Ki(wk2),.Li(wl2),.A(X[3]),.B(Y[3]),.K_n(K_o),.L_n(L_o));

endmodule

Test_COMP_4.v
`timescale 1ns/1ps // Definicion de los periodos de tiempo

module Test_COMP_4;

//******Definicion de data_types*****
//Entradas

reg X0,X1,X2,X3;
reg Y0,Y1,Y2,Y3;

//salidas
wire K_fin;
wire L_fin;

//*** Test_Module: Instanciacion del modulo bajo prueba ****

COMP_4 uut (
	.X({X0,X1,X2,X3}),  
	.Y({Y0,Y1,Y2,Y3}),
	.K_o(K_fin),
	.L_o(L_fin)
	);


//****Stimulus: Definicion de las señales que se aplicaran ****

initial
	begin
	$dumpfile("COMP_4.vcd");  // Volcado de los resultados de la simulación en el archivo COMP_4.vcd
	$dumpvars;
				// Colocacion de las posiciones segun vector X => A  Y => B 
				// Si A < B => K=0 L=1 , si A > B => K=1 L=0 , si A=B => K=L=1
				// casos de ejemplo para comprobar el funcionamiento optimo del sistema.

	     X0 = 0;X1 = 0;X2 = 0;X3 = 0;	Y0 = 0;Y1 = 0;Y2 = 0;Y3 = 0; 	// Xn[0,0,0,0] Yn[0,0,0,0] K = 1 L = 1
	 #15 X0 = 1;X1 = 0;X2 = 0;X3 = 0; 	Y0 = 1;Y1 = 0;Y2 = 0;Y3 = 0; 	// Xn[1,0,0,1] Yn[1,0,0,0] K = 1 L = 1 
	 #15 X0 = 1;X1 = 0;X2 = 1;X3 = 0; 	Y0 = 1;Y1 = 0;Y2 = 1;Y3 = 0; 	// Xn[1,0,1,0] Yn[1,0,1,0] K = 1 L = 1 
	 #15 X0 = 1;X1 = 1;X2 = 0;X3 = 0; 	Y0 = 1;Y1 = 1;Y2 = 1;Y3 = 0; 	// Xn[1,1,0,0] Yn[1,1,1,0] K = 0 L = 1
	 #15 X0 = 0;X1 = 0;X2 = 0;X3 = 0; 	Y0 = 1;Y1 = 0;Y2 = 0;Y3 = 0; 	// Xn[0,0,0,0] Yn[1,0,0,0] k = 0 L = 1
	 #15 X0 = 1;X1 = 1;X2 = 0;X3 = 0; 	Y0 = 1;Y1 = 1;Y2 = 0;Y3 = 0; 	// Xn[1,1,0,0] Yn[1,1,0,0] K = 1 L = 1
	 #15 X0 = 1;X1 = 1;X2 = 0;X3 = 0; 	Y0 = 0;Y1 = 0;Y2 = 1;Y3 = 1; 	// Xn[1,1,0,0] Yn[0,0,1,1] K = 1 L = 0 
	 #15 X0 = 0;X1 = 0;X2 = 1;X3 = 1; 	Y0 = 1;Y1 = 1;Y2 = 0;Y3 = 0; 	// Xn[0,0,1,1] Yn[1,1,0,0] K = 0 L = 1
	 #15 X0 = 1;X1 = 1;X2 = 1;X3 = 1; 	Y0 = 1;Y1 = 1;Y2 = 1;Y3 = 1; 	// Xn[1,1,1,1] Yn[1,1,1,1] K = 1 L = 1
	 #15 X0 = 0;X1 = 0;X2 = 0;X3 = 0; 	Y0 = 1;Y1 = 1;Y2 = 1;Y3 = 1; 	// Xn[0,0,0,0] Yn[1,1,1,1] K = 0 L = 1
	 #15 X0 = 1;X1 = 0;X2 = 0;X3 = 0; 	Y0 = 0;Y1 = 1;Y2 = 1;Y3 = 1; 	// Xn[1,0,0,0] Yn[0,1,1,1] K = 1 L = 0
	 
	 
	 	end

initial
	begin
		$monitor("X: [%b, %b, %b, %b] Y: [%b, %b, %b, %b] K = %b  L = %b", //Monitoreo de salidas y entradas
		X0,X1,X2,X3,Y0,Y1,Y2,Y3, K_fin, L_fin);
	end

endmodule

COMP_4.vcd
$date
	Fri Dec 04 03:41:37 2020
$end
$version
	Icarus Verilog
$end
$timescale
	1ps
$end
$scope module Test_COMP_4 $end
$var wire 1 ! L_fin $end
$var wire 1 " K_fin $end
$var reg 1 # X0 $end
$var reg 1 $ X1 $end
$var reg 1 % X2 $end
$var reg 1 & X3 $end
$var reg 1 ' Y0 $end
$var reg 1 ( Y1 $end
$var reg 1 ) Y2 $end
$var reg 1 * Y3 $end
$scope module uut $end
$var wire 4 + X [3:0] $end
$var wire 4 , Y [3:0] $end
$var wire 1 - wl2 $end
$var wire 1 . wl1 $end
$var wire 1 / wl0 $end
$var wire 1 0 wk2 $end
$var wire 1 1 wk1 $end
$var wire 1 2 wk0 $end
$var wire 1 ! L_o $end
$var wire 1 " K_o $end
$scope module Comp_1 $end
$var wire 2 3 s [1:0] $end
$var wire 1 / L $end
$var wire 1 2 K $end
$scope module MUX4x1_K $end
$var wire 4 4 I [3:0] $end
$var wire 2 5 S [1:0] $end
$var reg 1 2 T $end
$upscope $end
$scope module MUX4x1_L $end
$var wire 4 6 I [3:0] $end
$var wire 2 7 S [1:0] $end
$var reg 1 / T $end
$upscope $end
$upscope $end
$scope module Ext_1 $end
$var wire 1 8 A $end
$var wire 1 9 B $end
$var wire 1 1 K_n $end
$var wire 1 2 Ki $end
$var wire 1 . L_n $end
$var wire 1 / Li $end
$upscope $end
$scope module Ext_2 $end
$var wire 1 : A $end
$var wire 1 ; B $end
$var wire 1 0 K_n $end
$var wire 1 1 Ki $end
$var wire 1 - L_n $end
$var wire 1 . Li $end
$upscope $end
$scope module Ext_3 $end
$var wire 1 < A $end
$var wire 1 = B $end
$var wire 1 " K_n $end
$var wire 1 0 Ki $end
$var wire 1 ! L_n $end
$var wire 1 - Li $end
$upscope $end
$upscope $end
$upscope $end
$enddefinitions $end
#0
$dumpvars
0=
0<
0;
0:
09
08
b0 7
b1101 6
b0 5
b1011 4
b0 3
12
11
10
1/
1.
1-
b0 ,
b0 +
0*
0)
0(
0'
0&
0%
0$
0#
1"
1!
$end
#15000
1=
1<
b1000 ,
1'
b1000 +
1#
#30000
19
18
b1010 ,
1)
b1010 +
1%
#45000
0"
00
01
1;
08
1:
b1110 ,
1(
0%
b1100 +
1$
#60000
10
11
09
0;
0:
0<
0)
b1000 ,
0(
0$
b0 +
0#
#75000
1"
1;
1:
1<
b1100 ,
1(
1$
b1100 +
1#
#90000
01
02
0-
0!
b10 5
b10 7
b1 3
19
0;
0=
1*
1)
0(
b11 ,
0'
#105000
11
00
0"
1!
0.
1-
12
0/
b1 5
b1 7
09
1;
1=
b10 3
18
0:
0<
0*
0)
1(
b1100 ,
1'
1&
1%
0$
b11 +
0#
#120000
1!
1.
1"
1-
1/
10
b11 5
b11 7
b11 3
19
1:
1<
1*
b1111 ,
1)
1$
b1111 +
1#
#135000
02
01
00
0"
b10 5
b10 7
b1 3
08
0:
0<
0&
0%
0$
b0 +
0#
#150000
1"
0!
0=
1<
b111 ,
0'
b1000 +
1#
